MANIFEST.in
README.rst
setup.py
mongodb_gridfs_beaker/__init__.py
mongodb_gridfs_beaker.egg-info/PKG-INFO
mongodb_gridfs_beaker.egg-info/SOURCES.txt
mongodb_gridfs_beaker.egg-info/dependency_links.txt
mongodb_gridfs_beaker.egg-info/entry_points.txt
mongodb_gridfs_beaker.egg-info/requires.txt
mongodb_gridfs_beaker.egg-info/top_level.txt
mongodb_gridfs_beaker.egg-info/zip-safe
tests/__init__.py
tests/test_default.py