Metadata-Version: 1.1
Name: mongodb-gridfs-beaker
Version: 0.5.2
Summary: Beaker backend to write sessions and caches to a MongoDB GridFS
Home-page: https://github.com/loucash/mongodb_gridfs_beaker
Author: Lukasz Biedrycki
Author-email: lukasz.biedrycki@gmail.com
License: New BSD License
Keywords: mongo mongodb gridfs beaker cache session
Platform: UNKNOWN
Classifier: Development Status :: 4 - Beta
Classifier: Environment :: Other Environment
Classifier: Environment :: Web Environment
Classifier: Intended Audience :: Developers
Classifier: License :: OSI Approved :: BSD License
Classifier: Operating System :: OS Independent
Classifier: Programming Language :: Python
Classifier: Topic :: Database
Classifier: Topic :: Utilities
Classifier: Topic :: Software Development :: Libraries :: Python Modules
Requires: pymongo
Requires: beaker
